visual_novel_toolkit/__init__.py
visual_novel_toolkit/cli.py
visual_novel_toolkit/drafts/__init__.py
visual_novel_toolkit/drafts/cli.py
visual_novel_toolkit/drafts/missed.py
visual_novel_toolkit/drafts/new.py
visual_novel_toolkit/events/__init__.py
visual_novel_toolkit/events/cli.py
visual_novel_toolkit/events/data.py
visual_novel_toolkit/events/exceptions.py
visual_novel_toolkit/events/load.py
visual_novel_toolkit/events/plot.py
visual_novel_toolkit/py.typed
visual_novel_toolkit/speller/__init__.py
visual_novel_toolkit/speller/check.py
visual_novel_toolkit/speller/cli.py
visual_novel_toolkit/speller/dictionaries.py
visual_novel_toolkit/speller/duplicates.py
visual_novel_toolkit/speller/exceptions.py
visual_novel_toolkit/speller/mistakes.py
visual_novel_toolkit/speller/proofread.py
visual_novel_toolkit/speller/review.py
visual_novel_toolkit/speller/sort.py
visual_novel_toolkit/speller/unused.py
visual_novel_toolkit/speller/words.py
visual_novel_toolkit/workspace.py
visual_novel_toolkit-1.20.1.dist-info/LICENSE
visual_novel_toolkit-1.20.1.dist-info/METADATA
visual_novel_toolkit-1.20.1.dist-info/WHEEL
visual_novel_toolkit-1.20.1.dist-info/entry_points.txt
visual_novel_toolkit-1.20.1.dist-info/RECORD
