Metadata-Version: 2.1
Name: visual-novel-toolkit
Version: 1.20.1
Summary: A set of useful tools to improve DX of visual novel games.
Home-page: https://pypi.org/project/visual-novel-toolkit
License: BSD-2-Clause
Author: Josiah Kaviani
Author-email: proofit404@gmail.com
Classifier: License :: OSI Approved :: BSD License
Classifier: Programming Language :: Python :: 2
Classifier: Programming Language :: Python :: 2.7
Classifier: Programming Language :: Python :: 3
Classifier: Programming Language :: Python :: 3.4
Classifier: Programming Language :: Python :: 3.5
Classifier: Programming Language :: Python :: 3.6
Classifier: Programming Language :: Python :: 3.7
Classifier: Programming Language :: Python :: 3.8
Classifier: Programming Language :: Python :: 3.9
Classifier: Programming Language :: Python :: 3.10
Classifier: Programming Language :: Python :: 3.11
Requires-Dist: beautifulsoup4
Requires-Dist: httpx
Requires-Dist: pyyaml
Requires-Dist: typer
Project-URL: Changelog, https://proofit404.github.io/visual-novel-toolkit/changelog
Project-URL: Documentation, https://proofit404.github.io/visual-novel-toolkit
Project-URL: Issues, https://github.com/proofit404/visual-novel-toolkit/issues
Project-URL: Repository, https://github.com/proofit404/visual-novel-toolkit
Project-URL: Twitter, https://twitter.com/proofit404
